{
    "categoryIndex": 0,
    "sectionIndex": 0,
    "title": "I'm looking forward to",
    "link": "http://www.talkenglish.com/lessondetails.aspx?ALID=2030",
    "lessonIndex": 28,
    "html": "\r\n<h1>\r\nI&apos;m looking forward to\r\n</h1>\r\nWhen telling someone that you are &apos;looking forward to&apos; you are saying that you are waiting or hoping for something, especially with pleasure.<br><br>Here are some examples:<br><br>&quot;<a href=\"http://www.talkenglish.com/AudioTE1/E30/sentence/E030S1.mp3\">I&apos;m looking forward to meeting you.</a>&quot;<br>&quot;<a href=\"http://www.talkenglish.com/AudioTE1/E30/sentence/E030S2.mp3\">I&apos;m looking forward to talking with you.</a>&quot;<br>&quot;<a href=\"http://www.talkenglish.com/AudioTE1/E30/sentence/E030S3.mp3\">I&apos;m looking forward to going on vacation.</a>&quot;<br>&quot;<a href=\"http://www.talkenglish.com/AudioTE1/E30/sentence/E030S4.mp3\">I&apos;m looking forward to spending time with my family.</a>&quot;<br>&quot;<a href=\"http://www.talkenglish.com/AudioTE1/E30/sentence/E030S5.mp3\">I&apos;m looking forward to learning the English language.</a>&quot;<br>&quot;<a href=\"http://www.talkenglish.com/AudioTE1/E30/sentence/E030S6.mp3\">I am looking forward to visiting another country.</a>&quot;<br>&quot;<a href=\"http://www.talkenglish.com/AudioTE1/E30/sentence/E030S7.mp3\">I am looking forward to having a family.</a>&quot;<br>&quot;<a href=\"http://www.talkenglish.com/AudioTE1/E30/sentence/E030S8.mp3\">I am looking forward to graduating from college.</a>&quot;<br>&quot;<a href=\"http://www.talkenglish.com/AudioTE1/E30/sentence/E030S9.mp3\">I am looking forward to watching the baseball game.</a>&quot;<br>&quot;<a href=\"http://www.talkenglish.com/AudioTE1/E30/sentence/E030S10.mp3\">I am looking forward to running in a race.</a>&quot;<br>\r\n"
}