{
    "categoryIndex": 5,
    "sectionIndex": 4,
    "title": "Now You're Talking",
    "link": "http://www.talkenglish.com/lessondetails.aspx?ALID=1012",
    "lessonIndex": 679,
    "html": "\r\n<h1>\r\nNow You&apos;re Talking\r\n</h1>\r\n<b>Meaning/Usage</b>: Used to agree with someone<br><br> <b>Explanation</b>: This is similar to &quot;you can say that again.&quot; &#xA0;When someone talks and talks and talks, and then finally says something you really like or agree with, you can say, &quot;now you&apos;re talking.&quot;<br><br>&quot;<a href=\"http://www.talkenglish.com/AudioTE1/P65/sentence/P65S1.mp3\">A cold drink sounds great, <b>now you&apos;re talking</b>!</a>&quot;<br>&quot;<a href=\"http://www.talkenglish.com/AudioTE1/P65/sentence/P65S2.mp3\"><b>Now you&apos;re talking</b>, the beach sounds relaxing.</a>&quot;<br>&quot;<a href=\"http://www.talkenglish.com/AudioTE1/P65/sentence/P65S3.mp3\"><b>Now you&apos;re talking</b>, I would love to go out to the club tonight.</a>&quot;<br><br><b>A.</b> &#xA0;&quot;<a href=\"http://www.talkenglish.com/AudioTE1/P65/sentence/P65S4.mp3\">I say instead of staying home for vacation we go to Mexico.</a>&quot;<br><b>B.</b> &#xA0;&quot;<a href=\"http://www.talkenglish.com/AudioTE1/P65/sentence/P65S5.mp3\"><b>Now you&apos;re talking</b>!</a>&quot;<br><br>Other Common Sentences<br><br>&quot;<a href=\"http://www.talkenglish.com/AudioTE1/P65/sentence/P65S6.mp3\">I agree.</a>&quot;<br>&quot;<a href=\"http://www.talkenglish.com/AudioTE1/P65/sentence/P65S7.mp3\">I like what you&apos;re saying.</a>&quot;<br><br>\r\n"
}