{
    "lessonIndex": 3,
    "categoryIndex": 0,
    "sectionIndex": 0,
    "title": "I'm + (verb)",
    "link": "http://www.talkenglish.com/lessondetails.aspx?ALID=2005",
    "html": "\r\n<h1>\r\nI&apos;m + (verb)\r\n</h1>\r\nI&apos;m&apos; is a contraction of the words &apos;I am.&apos; By adding a verb to &apos;I&apos;m&apos; this lets you express an action or occurrence about yourself.<br><br>Here are some examples:<br><br>&quot;<a href=\"http://www.talkenglish.com/AudioTE1/E05/sentence/E005S1.mp3\">I&apos;m eating lunch.</a>&quot;<br>&quot;<a href=\"http://www.talkenglish.com/AudioTE1/E05/sentence/E005S2.mp3\">I&apos;m brushing my teeth.</a>&quot;<br>&quot;<a href=\"http://www.talkenglish.com/AudioTE1/E05/sentence/E005S3.mp3\">I&apos;m scared.</a>&quot;<br>&quot;<a href=\"http://www.talkenglish.com/AudioTE1/E05/sentence/E005S4.mp3\">I&apos;m driving to work.</a>&quot;<br>&quot;<a href=\"http://www.talkenglish.com/AudioTE1/E05/sentence/E005S5.mp3\">I&apos;m crying.</a>&quot;<br>&quot;<a href=\"http://www.talkenglish.com/AudioTE1/E05/sentence/E005S6.mp3\">I&apos;m typing an email.</a>&quot;<br>&quot;<a href=\"http://www.talkenglish.com/AudioTE1/E05/sentence/E005S7.mp3\">I&apos;m cooking dinner.</a>&quot;<br>&quot;<a href=\"http://www.talkenglish.com/AudioTE1/E05/sentence/E005S8.mp3\">I&apos;m combing my hair.</a>&quot;<br>&quot;<a href=\"http://www.talkenglish.com/AudioTE1/E05/sentence/E005S9.mp3\">I&apos;m hanging a picture.</a>&quot;<br>&quot;<a href=\"http://www.talkenglish.com/AudioTE1/E05/sentence/E005S10.mp3\">I am texting.</a>&quot;<br>&quot;<a href=\"http://www.talkenglish.com/AudioTE1/E05/sentence/E005S11.mp3\">I am dancing.</a>&quot;<br>&quot;<a href=\"http://www.talkenglish.com/AudioTE1/E05/sentence/E005S12.mp3\">I am interested in the job.</a>&quot;<br>&quot;<a href=\"http://www.talkenglish.com/AudioTE1/E05/sentence/E005S13.mp3\">I am exercising.</a>&quot;<br>&quot;<a href=\"http://www.talkenglish.com/AudioTE1/E05/sentence/E005S14.mp3\">I am sad.</a>&quot;<br>&quot;<a href=\"http://www.talkenglish.com/AudioTE1/E05/sentence/E005S15.mp3\">I am learning.</a>&quot;<br>\r\n"
}