{
    "categoryIndex": 0,
    "sectionIndex": 2,
    "title": "What if + (subject + verb)",
    "link": "http://www.talkenglish.com/lessondetails.aspx?ALID=2075",
    "lessonIndex": 73,
    "html": "\r\n<h1>\r\nWhat if + (subject + verb)\r\n</h1>\r\nHere you are asking a question about &apos;in the event of&apos; or &apos;in the event that.&apos; Usually you are looking for an answer at the time of the question that is being asked.<br><br>Here are some examples:<br><br>&quot;<a href=\"http://www.talkenglish.com/AudioTE1/E75/sentence/E075S1.mp3\">What if I miss the bus?</a>&quot;<br>&quot;<a href=\"http://www.talkenglish.com/AudioTE1/E75/sentence/E075S2.mp3\">What if I were late to dinner?</a>&quot;<br>&quot;<a href=\"http://www.talkenglish.com/AudioTE1/E75/sentence/E075S3.mp3\">What if I called her tomorrow?</a>&quot;<br>&quot;<a href=\"http://www.talkenglish.com/AudioTE1/E75/sentence/E075S4.mp3\">What if I don&apos;t understand?</a>&quot;<br>&quot;<a href=\"http://www.talkenglish.com/AudioTE1/E75/sentence/E075S5.mp3\">What if someone sees me?</a>&quot;<br>&quot;<a href=\"http://www.talkenglish.com/AudioTE1/E75/sentence/E075S6.mp3\">What if no one is home?</a>&quot;<br>&quot;<a href=\"http://www.talkenglish.com/AudioTE1/E75/sentence/E075S7.mp3\">What if they decide to stay?</a>&quot;<br>&quot;<a href=\"http://www.talkenglish.com/AudioTE1/E75/sentence/E075S8.mp3\">What if it rains while we are camping?</a>&quot;<br>&quot;<a href=\"http://www.talkenglish.com/AudioTE1/E75/sentence/E075S9.mp3\">What if I do not finish on time?</a>&quot;<br>&quot;<a href=\"http://www.talkenglish.com/AudioTE1/E75/sentence/E075S10.mp3\">What if we introduce ourselves first?</a>&quot;<br>\r\n"
}