{
    "categoryIndex": 5,
    "sectionIndex": 7,
    "title": "Rise and Shine",
    "link": "http://www.talkenglish.com/lessondetails.aspx?ALID=1065",
    "lessonIndex": 732,
    "html": "\r\n<h1>\r\nRise and Shine\r\n</h1>\r\n<b>Meaning/Usage</b>: Phrase used to wake someone up nicely<br><br> <b>Explanation</b>: &quot;Rise&quot; means to get up and &quot;shine&quot; in this context means to &quot;act lively and do well.&quot;<br><br>&quot;<a href=\"http://www.talkenglish.com/AudioTE1/P118/sentence/P118S1.mp3\">It&apos;s time to <b>rise and shine</b> sweetheart.</a>&quot;<br>&quot;<a href=\"http://www.talkenglish.com/AudioTE1/P118/sentence/P118S2.mp3\">You&apos;d better <b>rise and shine</b> or you&apos;ll be late for work.</a>&quot;<br>&quot;<a href=\"http://www.talkenglish.com/AudioTE1/P118/sentence/P118S3.mp3\"><b>Rise and shine</b> sleepy head, it&apos;s time for breakfast.</a>&quot;<br><br><b>A.</b> &#xA0;&quot;<a href=\"http://www.talkenglish.com/AudioTE1/P118/sentence/P118S4.mp3\"><b>Rise and shine</b>! It&apos;s time to get up!</a>&quot;<br><b>B.</b> &#xA0;&quot;<a href=\"http://www.talkenglish.com/AudioTE1/P118/sentence/P118S5.mp3\">Can&apos;t I just stay in bed a bit longer?</a>&quot;<br><b>A.</b> &#xA0;&quot;<a href=\"http://www.talkenglish.com/AudioTE1/P118/sentence/P118S6.mp3\">If you do you will be late for work.</a>&quot;<br><br>Other Common Sentences<br><br>&quot;<a href=\"http://www.talkenglish.com/AudioTE1/P118/sentence/P118S7.mp3\">It&apos;s time to wake up.</a>&quot;<br>&quot;<a href=\"http://www.talkenglish.com/AudioTE1/P118/sentence/P118S8.mp3\">Get out of bed.</a>&quot;<br><br>\r\n"
}